agent_network/__init__.py
agent_network/base.py
agent_network/base_chain_agent.py
agent_network/utils_agent.py
agent_network/message/__init__.py
agent_network/message/utils.py
agent_network-0.0.1.dist-info/LICENSE
agent_network-0.0.1.dist-info/METADATA
agent_network-0.0.1.dist-info/WHEEL
agent_network-0.0.1.dist-info/top_level.txt
agent_network-0.0.1.dist-info/RECORD
