Metadata-Version: 2.1
Name: agent-network
Version: 0.0.1
Summary: An Agent Self-Organizing Intelligent Network
Home-page: https://github.com/WhuAgent/agent-network.git
Author: WhuAgent
Author-email: zhuyuhan2333@whu.edu.cn
Classifier: Programming Language :: Python :: 3
Classifier: License :: OSI Approved :: Apache Software License
Classifier: Operating System :: OS Independent
Requires-Python: >=3.10
License-File: LICENSE
Requires-Dist: annotated-types (==0.7.0)
Requires-Dist: anyio (==4.4.0)
Requires-Dist: certifi (==2024.8.30)
Requires-Dist: distro (==1.9.0)
Requires-Dist: exceptiongroup (==1.2.2)
Requires-Dist: h11 (==0.14.0)
Requires-Dist: httpcore (==1.0.5)
Requires-Dist: httpx (==0.27.2)
Requires-Dist: idna (==3.8)
Requires-Dist: jiter (==0.5.0)
Requires-Dist: numpy (==2.1.1)
Requires-Dist: openai (==1.44.1)
Requires-Dist: pydantic (==2.9.1)
Requires-Dist: pydantic-core (==2.23.3)
Requires-Dist: PyYAML (==6.0.2)
Requires-Dist: sniffio (==1.3.1)
Requires-Dist: tqdm (==4.66.5)
Requires-Dist: typing-extensions (==4.12.2)
